[
{
"name":"543",
"
country":"Deutschland","twitter":"lvAktuelleslevel1"},{"name":"543","country":"Deutschland","twitter":"lvAktuelleslevel1"},{"name":"543","country":"Deutschland","twitter":"lvFAIL_level1"},{"name":"543","country":"Deutschland","twitter":"lvFAIL_level1"},{"name":"543","country":"Deutschland","twitter":"lvMaxlevel1"},{"name":"543","country":"Deutschland","twitter":"lvMaxlevel1"},{"name":"543","country":"Deutschland","twitter":"lvMaxlevel2"},{"name":"543","country":"Deutschland","twitter":"lvMaxlevel2"},{"name":"543","country":"Deutschland","twitter":"lvAktuelleslevel2"},{"name":"543","country":"Deutschland","twitter":"lvAktuelleslevel2"},{"name":"543","country":"Deutschland","twitter":"lvMaxlevel2"},{"name":"543","country":"Deutschland","twitter":"lvMaxlevel2"},{"name":"543","country":"Deutschland","twitter":"lvMaxlevel1"},{"name":"543","country":"Deutschland","twitter":"lvMaxlevel1"},{"name":"543","country":"Deutschland","twitter":"lvMaxlevel1"},{"name":"543","country":"Deutschland","twitter":"lvMaxlevel1"},{"name":"543","country":"Deutschland","twitter":"lvMaxlevel1"},{"name":"543","country":"Deutschland","twitter":"lvMaxlevel1"},{"name":"543","country":"Deutschland","twitter":"lvMaxlevel1"},{"name":"543","country":"Deutschland","twitter":"lvMaxlevel1"},{"name":"Testando","country":"Brasil","twitter":"Num tem"}
